clip/__init__.py
clip/bpe_simple_vocab_16e6.txt.gz
clip/clip.py
clip/model.py
clip/simple_tokenizer.py
clip_ea-1.0.dist-info/LICENSE
clip_ea-1.0.dist-info/METADATA
clip_ea-1.0.dist-info/WHEEL
clip_ea-1.0.dist-info/top_level.txt
clip_ea-1.0.dist-info/RECORD
