Metadata-Version: 2.1
Name: clip-ea
Version: 1.0
Author: OpenAI
License-File: LICENSE
Requires-Dist: ftfy
Requires-Dist: regex
Requires-Dist: tqdm
Requires-Dist: torch
Requires-Dist: torchvision
Provides-Extra: dev
Requires-Dist: pytest ; extra == 'dev'
